py_flowcheck/__init__.py
py_flowcheck/config.py
py_flowcheck/decorators.py
py_flowcheck/logging_config.py
py_flowcheck/monitoring.py
py_flowcheck/schema.py
py_flowcheck/integrations/__init__.py
py_flowcheck/integrations/celery.py
py_flowcheck/integrations/fastapi.py
pyflowcheck_validation-0.1.0.dist-info/METADATA
pyflowcheck_validation-0.1.0.dist-info/WHEEL
pyflowcheck_validation-0.1.0.dist-info/licenses/LICENSE
pyflowcheck_validation-0.1.0.dist-info/RECORD
