Metadata-Version: 2.4
Name: pyflowcheck-validation
Version: 0.1.0
Summary: A lightweight runtime contract validation library for Python backends and data pipelines.
Author-email: Your Name <your.email@example.com>
License: MIT
License-File: LICENSE
Requires-Python: >=3.9
Requires-Dist: celery
Requires-Dist: fastapi
Requires-Dist: flask
Requires-Dist: mypy
Requires-Dist: pydantic
Requires-Dist: pytest
Requires-Dist: ruff
Requires-Dist: uvicorn
